AppriseLibrary/AppriseLibrary.py
AppriseLibrary/__init__.py
robotframework_apprise-0.3.1.dist-info/LICENSE
robotframework_apprise-0.3.1.dist-info/METADATA
robotframework_apprise-0.3.1.dist-info/WHEEL
robotframework_apprise-0.3.1.dist-info/top_level.txt
robotframework_apprise-0.3.1.dist-info/RECORD
