Metadata-Version: 2.1
Name: robotframework-apprise
Version: 0.3.1
Summary: Robot Framework keywords for the 'Apprise' push messaging library
Home-page: https://github.com/joergschultzelutter/robotframework-apprise
Author: Joerg Schultze-Lutter
Author-email: joerg.schultze.lutter@gmail.com
License: GNU General Public License v3 (GPLv3)
Keywords: Notifications,Notification Service,Push Notifications,Notifier,Alerts,Robot Framework
Classifier: Intended Audience :: Developers
Classifier: Programming Language :: Python :: 3
Classifier: Natural Language :: English
Classifier: License :: OSI Approved :: GNU General Public License v3 (GPLv3)
Classifier: Operating System :: OS Independent
Classifier: Development Status :: 4 - Beta
Classifier: Framework :: Robot Framework
Classifier: Framework :: Robot Framework :: Library
Classifier: Topic :: Software Development
Classifier: Topic :: Software Development :: Testing
Classifier: Topic :: Software Development :: Quality Assurance
License-File: LICENSE
Requires-Dist: robotframework (>=4.0.1)
Requires-Dist: apprise (>=0.9.6)
